evil_pkk/__init__.py
evil_pkk-0.5.dist-info/METADATA
evil_pkk-0.5.dist-info/WHEEL
evil_pkk-0.5.dist-info/top_level.txt
evil_pkk-0.5.dist-info/RECORD
