Metadata-Version: 2.2
Name: evil-pkk
Version: 0.5
Summary: Just a harmless package :)
Dynamic: summary
